llmapi/__init__.py
llmapi-1.0.9.dist-info/LICENSE
llmapi-1.0.9.dist-info/METADATA
llmapi-1.0.9.dist-info/WHEEL
llmapi-1.0.9.dist-info/entry_points.txt
llmapi-1.0.9.dist-info/top_level.txt
llmapi-1.0.9.dist-info/RECORD
